odoo8_addon_crm_rma_stock_location-8.0.1.1.0-py3.8-nspkg.pth
odoo_addons/crm_rma_stock_location/README.rst
odoo_addons/crm_rma_stock_location/__init__.py
odoo_addons/crm_rma_stock_location/__openerp__.py
odoo_addons/crm_rma_stock_location/init_hooks.py
odoo_addons/crm_rma_stock_location/demo/stock_inventory.xml
odoo_addons/crm_rma_stock_location/demo/stock_location.xml
odoo_addons/crm_rma_stock_location/i18n/am.po
odoo_addons/crm_rma_stock_location/i18n/ar.po
odoo_addons/crm_rma_stock_location/i18n/bg.po
odoo_addons/crm_rma_stock_location/i18n/bs.po
odoo_addons/crm_rma_stock_location/i18n/ca.po
odoo_addons/crm_rma_stock_location/i18n/ca_ES.po
odoo_addons/crm_rma_stock_location/i18n/crm_rma_stock_location.pot
odoo_addons/crm_rma_stock_location/i18n/cs.po
odoo_addons/crm_rma_stock_location/i18n/da.po
odoo_addons/crm_rma_stock_location/i18n/de.po
odoo_addons/crm_rma_stock_location/i18n/el_GR.po
odoo_addons/crm_rma_stock_location/i18n/en_AU.po
odoo_addons/crm_rma_stock_location/i18n/en_GB.po
odoo_addons/crm_rma_stock_location/i18n/es.po
odoo_addons/crm_rma_stock_location/i18n/es_AR.po
odoo_addons/crm_rma_stock_location/i18n/es_CL.po
odoo_addons/crm_rma_stock_location/i18n/es_CO.po
odoo_addons/crm_rma_stock_location/i18n/es_CR.po
odoo_addons/crm_rma_stock_location/i18n/es_DO.po
odoo_addons/crm_rma_stock_location/i18n/es_EC.po
odoo_addons/crm_rma_stock_location/i18n/es_ES.po
odoo_addons/crm_rma_stock_location/i18n/es_MX.po
odoo_addons/crm_rma_stock_location/i18n/es_PA.po
odoo_addons/crm_rma_stock_location/i18n/es_PE.po
odoo_addons/crm_rma_stock_location/i18n/es_PY.po
odoo_addons/crm_rma_stock_location/i18n/es_VE.po
odoo_addons/crm_rma_stock_location/i18n/et.po
odoo_addons/crm_rma_stock_location/i18n/eu.po
odoo_addons/crm_rma_stock_location/i18n/fa.po
odoo_addons/crm_rma_stock_location/i18n/fi.po
odoo_addons/crm_rma_stock_location/i18n/fr.po
odoo_addons/crm_rma_stock_location/i18n/fr_CA.po
odoo_addons/crm_rma_stock_location/i18n/fr_CH.po
odoo8_addon_crm_rma_stock_location-8.0.1.1.0.dist-info/METADATA
odoo8_addon_crm_rma_stock_location-8.0.1.1.0.dist-info/WHEEL
odoo8_addon_crm_rma_stock_location-8.0.1.1.0.dist-info/namespace_packages.txt
odoo8_addon_crm_rma_stock_location-8.0.1.1.0.dist-info/top_level.txt
odoo8_addon_crm_rma_stock_location-8.0.1.1.0.dist-info/RECORD
