Metadata-Version: 2.1
Name: odoo8-addon-crm-rma-stock-location
Version: 8.0.1.1.0
Summary: RMA Stock Location
Home-page: http://www.camptocamp.com,http://www.vauxoo.com
Author: Akretion,Vauxoo,Camptocamp,Odoo Community Association (OCA)
Author-email: support@odoo-community.org
License: AGPL-3
Platform: UNKNOWN
Classifier: Programming Language :: Python
Classifier: Framework :: Odoo
Classifier: Framework :: Odoo :: 8.0
Classifier: License :: OSI Approved :: GNU Affero General Public License v3
Requires-Python: ~=2.7
Requires-Dist: odoo8-addon-crm-claim-rma
Requires-Dist: odoo8-addon-crm-rma-location
Requires-Dist: odoo (<9.0a,>=8.0a)
